{
  "$schema": "https://gremorie.com/schema/registry-item.json",
  "name": "rx-prompt-input",
  "type": "registry:block",
  "framework": "rx",
  "title": "Prompt Input (React)",
  "description": "PromptInput family for AI chat surfaces - state machine, drag-drop, paste-to-attach, status-driven Submit. Full Bridge parity: InputGroup composition (InputGroupButton + InputGroupTextarea), ActionMenu (dropdown), ModelSelector (select), attachment HoverCard previews, Speech button (Web Speech API), Command palette wrappers, Cmd+K floating palette via CommandDialog, and Tabs panels.",
  "categories": [
    "ai",
    "forms"
  ],
  "dependencies": [
    "lucide-react",
    "@gremorie/rx-core",
    "@gremorie/rx-forms",
    "@gremorie/rx-overlays"
  ],
  "devDependencies": [],
  "registryDependencies": [
    "rx-utils",
    "rx-button",
    "rx-input-group",
    "rx-select",
    "rx-dialog",
    "rx-dropdown-menu",
    "rx-hover-card",
    "rx-command",
    "rx-attachments"
  ],
  "files": [
    {
      "path": "src/lib/prompt-input/prompt-input.tsx",
      "content": "'use client';\n\nimport {\n  type ChangeEvent,\n  type ChangeEventHandler,\n  Children,\n  type ClipboardEventHandler,\n  type ComponentProps,\n  createContext,\n  type FormEvent,\n  type FormEventHandler,\n  Fragment,\n  type HTMLAttributes,\n  type KeyboardEventHandler,\n  type PropsWithChildren,\n  type ReactNode,\n  type RefObject,\n  useCallback,\n  useContext,\n  useEffect,\n  useMemo,\n  useRef,\n  useState,\n} from 'react';\n\nimport { cn } from '@gremorie/rx-core';\nimport {\n  InputGroup,\n  InputGroupAddon,\n  InputGroupButton,\n  InputGroupTextarea,\n  Select,\n  SelectContent,\n  SelectItem,\n  SelectTrigger,\n  SelectValue,\n} from '@gremorie/rx-forms';\nimport {\n  Command,\n  CommandEmpty,\n  CommandGroup,\n  CommandInput,\n  CommandItem,\n  CommandList,\n  CommandSeparator,\n  DropdownMenu,\n  DropdownMenuContent,\n  DropdownMenuItem,\n  DropdownMenuTrigger,\n  HoverCard,\n  HoverCardContent,\n  HoverCardTrigger,\n  Tooltip,\n  TooltipContent,\n  TooltipProvider,\n  TooltipTrigger,\n} from '@gremorie/rx-overlays';\nimport {\n  CornerDownLeftIcon,\n  ImageIcon,\n  Loader2Icon,\n  MicIcon,\n  PaperclipIcon,\n  PlusIcon,\n  SquareIcon,\n  XIcon,\n} from 'lucide-react';\n\nimport {\n  Attachment,\n  AttachmentHoverCard,\n  AttachmentHoverCardContent,\n  AttachmentHoverCardTrigger,\n  AttachmentInfo,\n  AttachmentPreview,\n  AttachmentRemove,\n  Attachments,\n  type AttachmentVariant,\n  getAttachmentLabel,\n  getMediaCategory,\n} from '../attachments';\n\n// ============================================================================\n// Types - portable subset of FileUIPart / ChatStatus (no @ai-sdk dep here)\n// ============================================================================\n\nexport type ChatStatus = 'ready' | 'submitted' | 'streaming' | 'error';\n\nexport type FileUIPart = {\n  type: 'file';\n  url: string;\n  mediaType: string;\n  filename?: string;\n};\n\nexport type AttachmentFile = FileUIPart & { id: string };\n\nfunction generateId(): string {\n  if (typeof crypto !== 'undefined' && 'randomUUID' in crypto) {\n    return crypto.randomUUID();\n  }\n  return `attachment-${Date.now().toString(36)}-${Math.random()\n    .toString(36)\n    .slice(2, 8)}`;\n}\n\n// ============================================================================\n// Provider Context & Types\n// ============================================================================\n\nexport type AttachmentsContext = {\n  files: AttachmentFile[];\n  add: (files: File[] | FileList) => void;\n  remove: (id: string) => void;\n  clear: () => void;\n  openFileDialog: () => void;\n  fileInputRef: RefObject<HTMLInputElement | null>;\n};\n\nexport type TextInputContext = {\n  value: string;\n  setInput: (v: string) => void;\n  clear: () => void;\n};\n\nexport type PromptInputControllerProps = {\n  textInput: TextInputContext;\n  attachments: AttachmentsContext;\n  /** INTERNAL: Allows PromptInput to register its file input + open callback */\n  __registerFileInput: (\n    ref: RefObject<HTMLInputElement | null>,\n    open: () => void,\n  ) => void;\n};\n\nconst PromptInputController = createContext<PromptInputControllerProps | null>(\n  null,\n);\nconst ProviderAttachmentsContext = createContext<AttachmentsContext | null>(\n  null,\n);\n\nexport const usePromptInputController = () => {\n  const ctx = useContext(PromptInputController);\n  if (!ctx) {\n    throw new Error(\n      'Wrap your component inside <PromptInputProvider> to use usePromptInputController().',\n    );\n  }\n  return ctx;\n};\n\nconst useOptionalPromptInputController = () =>\n  useContext(PromptInputController);\n\nexport const useProviderAttachments = () => {\n  const ctx = useContext(ProviderAttachmentsContext);\n  if (!ctx) {\n    throw new Error(\n      'Wrap your component inside <PromptInputProvider> to use useProviderAttachments().',\n    );\n  }\n  return ctx;\n};\n\nconst useOptionalProviderAttachments = () =>\n  useContext(ProviderAttachmentsContext);\n\nexport type PromptInputProviderProps = PropsWithChildren<{\n  initialInput?: string;\n}>;\n\n/**\n * Optional global provider that lifts PromptInput state outside of PromptInput.\n * If you don't use it, PromptInput stays fully self-managed.\n */\nexport function PromptInputProvider({\n  initialInput: initialTextInput = '',\n  children,\n}: PromptInputProviderProps) {\n  const [textInput, setTextInput] = useState(initialTextInput);\n  const clearInput = useCallback(() => setTextInput(''), []);\n\n  const [attachmentFiles, setAttachmentFiles] = useState<AttachmentFile[]>([]);\n  const fileInputRef = useRef<HTMLInputElement | null>(null);\n  const openRef = useRef<() => void>(() => {\n    // intentional no-op until a file input is registered\n  });\n\n  const add = useCallback((files: File[] | FileList) => {\n    const incoming = Array.from(files);\n    if (incoming.length === 0) {\n      return;\n    }\n    setAttachmentFiles((prev) =>\n      prev.concat(\n        incoming.map((file) => ({\n          id: generateId(),\n          type: 'file' as const,\n          url: URL.createObjectURL(file),\n          mediaType: file.type,\n          filename: file.name,\n        })),\n      ),\n    );\n  }, []);\n\n  const remove = useCallback((id: string) => {\n    setAttachmentFiles((prev) => {\n      const found = prev.find((f) => f.id === id);\n      if (found?.url) {\n        URL.revokeObjectURL(found.url);\n      }\n      return prev.filter((f) => f.id !== id);\n    });\n  }, []);\n\n  const clear = useCallback(() => {\n    setAttachmentFiles((prev) => {\n      for (const f of prev) {\n        if (f.url) {\n          URL.revokeObjectURL(f.url);\n        }\n      }\n      return [];\n    });\n  }, []);\n\n  const attachmentsRef = useRef(attachmentFiles);\n  attachmentsRef.current = attachmentFiles;\n\n  useEffect(() => {\n    return () => {\n      for (const f of attachmentsRef.current) {\n        if (f.url) {\n          URL.revokeObjectURL(f.url);\n        }\n      }\n    };\n  }, []);\n\n  const openFileDialog = useCallback(() => {\n    openRef.current?.();\n  }, []);\n\n  const attachments = useMemo<AttachmentsContext>(\n    () => ({\n      files: attachmentFiles,\n      add,\n      remove,\n      clear,\n      openFileDialog,\n      fileInputRef,\n    }),\n    [attachmentFiles, add, remove, clear, openFileDialog],\n  );\n\n  const __registerFileInput = useCallback(\n    (ref: RefObject<HTMLInputElement | null>, open: () => void) => {\n      fileInputRef.current = ref.current;\n      openRef.current = open;\n    },\n    [],\n  );\n\n  const controller = useMemo<PromptInputControllerProps>(\n    () => ({\n      textInput: {\n        value: textInput,\n        setInput: setTextInput,\n        clear: clearInput,\n      },\n      attachments,\n      __registerFileInput,\n    }),\n    [textInput, clearInput, attachments, __registerFileInput],\n  );\n\n  return (\n    <PromptInputController.Provider value={controller}>\n      <ProviderAttachmentsContext.Provider value={attachments}>\n        {children}\n      </ProviderAttachmentsContext.Provider>\n    </PromptInputController.Provider>\n  );\n}\n\n// ============================================================================\n// Component Context & Hooks\n// ============================================================================\n\nconst LocalAttachmentsContext = createContext<AttachmentsContext | null>(null);\n\nexport const usePromptInputAttachments = () => {\n  const provider = useOptionalProviderAttachments();\n  const local = useContext(LocalAttachmentsContext);\n  const context = provider ?? local;\n  if (!context) {\n    throw new Error(\n      'usePromptInputAttachments must be used within a PromptInput or PromptInputProvider',\n    );\n  }\n  return context;\n};\n\n// ============================================================================\n// PromptInputAttachment - one attachment chip with HoverCard preview\n// ============================================================================\n\nexport type PromptInputAttachmentProps = HTMLAttributes<HTMLDivElement> & {\n  data: AttachmentFile;\n  className?: string;\n};\n\nexport function PromptInputAttachment({\n  data,\n  className,\n  ...props\n}: PromptInputAttachmentProps) {\n  const attachments = usePromptInputAttachments();\n  const mediaCategory = getMediaCategory(data);\n  const label = getAttachmentLabel(data);\n\n  // Delegates to the standalone Attachment module (inline variant) so the chip\n  // stays in lock-step with the canonical component used elsewhere (messages,\n  // file lists). The inline layout context comes from PromptInputAttachments.\n  return (\n    <AttachmentHoverCard>\n      <AttachmentHoverCardTrigger asChild>\n        <Attachment\n          className={className}\n          data={data}\n          onRemove={() => attachments.remove(data.id)}\n          {...props}\n        >\n          <div className=\"relative size-5 shrink-0\">\n            <div className=\"absolute inset-0 transition-opacity group-hover:opacity-0\">\n              <AttachmentPreview />\n            </div>\n            <AttachmentRemove className=\"absolute inset-0\" />\n          </div>\n          <AttachmentInfo />\n        </Attachment>\n      </AttachmentHoverCardTrigger>\n      <AttachmentHoverCardContent>\n        <div className=\"space-y-3\">\n          {mediaCategory === 'image' && data.url ? (\n            <div className=\"flex max-h-96 w-80 items-center justify-center overflow-hidden rounded-md border\">\n              <img\n                alt={label}\n                className=\"max-h-full max-w-full object-contain\"\n                height={384}\n                src={data.url}\n                width={320}\n              />\n            </div>\n          ) : null}\n          <div className=\"space-y-1 px-0.5\">\n            <h4 className=\"font-semibold text-sm leading-none\">{label}</h4>\n            {data.mediaType ? (\n              <p className=\"font-mono text-muted-foreground text-xs\">\n                {data.mediaType}\n              </p>\n            ) : null}\n          </div>\n        </div>\n      </AttachmentHoverCardContent>\n    </AttachmentHoverCard>\n  );\n}\n\n// ============================================================================\n// PromptInputAttachments - container that renders each file via a child fn\n// ============================================================================\n\nexport type PromptInputAttachmentsProps = Omit<\n  HTMLAttributes<HTMLDivElement>,\n  'children'\n> & {\n  children: (attachment: AttachmentFile) => ReactNode;\n  /** Layout variant for the attachment row. Defaults to `inline` badges. */\n  variant?: AttachmentVariant;\n};\n\nexport function PromptInputAttachments({\n  children,\n  className,\n  variant = 'inline',\n  ...props\n}: PromptInputAttachmentsProps) {\n  const attachments = usePromptInputAttachments();\n\n  if (!attachments.files.length) {\n    return null;\n  }\n\n  return (\n    <Attachments\n      className={cn('w-full p-3', className)}\n      variant={variant}\n      {...props}\n    >\n      {attachments.files.map((file) => (\n        <Fragment key={file.id}>{children(file)}</Fragment>\n      ))}\n    </Attachments>\n  );\n}\n\n// ============================================================================\n// PromptInputActionAddAttachments - drop-in DropdownMenuItem\n// ============================================================================\n\nexport type PromptInputActionAddAttachmentsProps = ComponentProps<\n  typeof DropdownMenuItem\n> & {\n  label?: string;\n};\n\nexport const PromptInputActionAddAttachments = ({\n  label = 'Add photos or files',\n  ...props\n}: PromptInputActionAddAttachmentsProps) => {\n  const attachments = usePromptInputAttachments();\n\n  return (\n    <DropdownMenuItem\n      {...props}\n      onSelect={(e) => {\n        e.preventDefault();\n        attachments.openFileDialog();\n      }}\n    >\n      <ImageIcon className=\"mr-2 size-4\" /> {label}\n    </DropdownMenuItem>\n  );\n};\n\n// ============================================================================\n// PromptInput - form root with state machine\n// ============================================================================\n\nexport type PromptInputMessage = {\n  text: string;\n  files: FileUIPart[];\n};\n\nexport type PromptInputProps = Omit<\n  HTMLAttributes<HTMLFormElement>,\n  'onSubmit' | 'onError'\n> & {\n  accept?: string;\n  multiple?: boolean;\n  globalDrop?: boolean;\n  syncHiddenInput?: boolean;\n  maxFiles?: number;\n  maxFileSize?: number;\n  onError?: (err: {\n    code: 'max_files' | 'max_file_size' | 'accept';\n    message: string;\n  }) => void;\n  onSubmit: (\n    message: PromptInputMessage,\n    event: FormEvent<HTMLFormElement>,\n  ) => void | Promise<void>;\n};\n\nexport const PromptInput = ({\n  className,\n  accept,\n  multiple,\n  globalDrop,\n  syncHiddenInput,\n  maxFiles,\n  maxFileSize,\n  onError,\n  onSubmit,\n  children,\n  ...props\n}: PromptInputProps) => {\n  const controller = useOptionalPromptInputController();\n  const usingProvider = !!controller;\n\n  const inputRef = useRef<HTMLInputElement | null>(null);\n  const formRef = useRef<HTMLFormElement | null>(null);\n\n  const [items, setItems] = useState<AttachmentFile[]>([]);\n  const files = usingProvider ? controller.attachments.files : items;\n\n  const filesRef = useRef(files);\n  filesRef.current = files;\n\n  const openFileDialogLocal = useCallback(() => {\n    inputRef.current?.click();\n  }, []);\n\n  const matchesAccept = useCallback(\n    (f: File) => {\n      if (!accept || accept.trim() === '') {\n        return true;\n      }\n      const patterns = accept\n        .split(',')\n        .map((s) => s.trim())\n        .filter(Boolean);\n      return patterns.some((pattern) => {\n        if (pattern.endsWith('/*')) {\n          const prefix = pattern.slice(0, -1);\n          return f.type.startsWith(prefix);\n        }\n        return f.type === pattern;\n      });\n    },\n    [accept],\n  );\n\n  const addLocal = useCallback(\n    (fileList: File[] | FileList) => {\n      const incoming = Array.from(fileList);\n      const accepted = incoming.filter((f) => matchesAccept(f));\n      if (incoming.length && accepted.length === 0) {\n        onError?.({\n          code: 'accept',\n          message: 'No files match the accepted types.',\n        });\n        return;\n      }\n      const withinSize = (f: File) =>\n        maxFileSize ? f.size <= maxFileSize : true;\n      const sized = accepted.filter(withinSize);\n      if (accepted.length > 0 && sized.length === 0) {\n        onError?.({\n          code: 'max_file_size',\n          message: 'All files exceed the maximum size.',\n        });\n        return;\n      }\n\n      setItems((prev) => {\n        const capacity =\n          typeof maxFiles === 'number'\n            ? Math.max(0, maxFiles - prev.length)\n            : undefined;\n        const capped =\n          typeof capacity === 'number' ? sized.slice(0, capacity) : sized;\n        if (typeof capacity === 'number' && sized.length > capacity) {\n          onError?.({\n            code: 'max_files',\n            message: 'Too many files. Some were not added.',\n          });\n        }\n        const next: AttachmentFile[] = [];\n        for (const file of capped) {\n          next.push({\n            id: generateId(),\n            type: 'file',\n            url: URL.createObjectURL(file),\n            mediaType: file.type,\n            filename: file.name,\n          });\n        }\n        return prev.concat(next);\n      });\n    },\n    [matchesAccept, maxFiles, maxFileSize, onError],\n  );\n\n  const removeLocal = useCallback(\n    (id: string) =>\n      setItems((prev) => {\n        const found = prev.find((file) => file.id === id);\n        if (found?.url) {\n          URL.revokeObjectURL(found.url);\n        }\n        return prev.filter((file) => file.id !== id);\n      }),\n    [],\n  );\n\n  const clearLocal = useCallback(\n    () =>\n      setItems((prev) => {\n        for (const file of prev) {\n          if (file.url) {\n            URL.revokeObjectURL(file.url);\n          }\n        }\n        return [];\n      }),\n    [],\n  );\n\n  const add = usingProvider ? controller.attachments.add : addLocal;\n  const remove = usingProvider ? controller.attachments.remove : removeLocal;\n  const clear = usingProvider ? controller.attachments.clear : clearLocal;\n  const openFileDialog = usingProvider\n    ? controller.attachments.openFileDialog\n    : openFileDialogLocal;\n\n  useEffect(() => {\n    if (!usingProvider) return;\n    controller.__registerFileInput(inputRef, () => inputRef.current?.click());\n  }, [usingProvider, controller]);\n\n  useEffect(() => {\n    if (syncHiddenInput && inputRef.current && files.length === 0) {\n      inputRef.current.value = '';\n    }\n  }, [files, syncHiddenInput]);\n\n  useEffect(() => {\n    const form = formRef.current;\n    if (!form) return;\n    if (globalDrop) return;\n\n    const onDragOver = (e: DragEvent) => {\n      if (e.dataTransfer?.types?.includes('Files')) {\n        e.preventDefault();\n      }\n    };\n    const onDrop = (e: DragEvent) => {\n      if (e.dataTransfer?.types?.includes('Files')) {\n        e.preventDefault();\n      }\n      if (e.dataTransfer?.files && e.dataTransfer.files.length > 0) {\n        add(e.dataTransfer.files);\n      }\n    };\n    form.addEventListener('dragover', onDragOver);\n    form.addEventListener('drop', onDrop);\n    return () => {\n      form.removeEventListener('dragover', onDragOver);\n      form.removeEventListener('drop', onDrop);\n    };\n  }, [add, globalDrop]);\n\n  useEffect(() => {\n    if (!globalDrop) return;\n    const onDragOver = (e: DragEvent) => {\n      if (e.dataTransfer?.types?.includes('Files')) {\n        e.preventDefault();\n      }\n    };\n    const onDrop = (e: DragEvent) => {\n      if (e.dataTransfer?.types?.includes('Files')) {\n        e.preventDefault();\n      }\n      if (e.dataTransfer?.files && e.dataTransfer.files.length > 0) {\n        add(e.dataTransfer.files);\n      }\n    };\n    document.addEventListener('dragover', onDragOver);\n    document.addEventListener('drop', onDrop);\n    return () => {\n      document.removeEventListener('dragover', onDragOver);\n      document.removeEventListener('drop', onDrop);\n    };\n  }, [add, globalDrop]);\n\n  useEffect(\n    () => () => {\n      if (!usingProvider) {\n        for (const f of filesRef.current) {\n          if (f.url) URL.revokeObjectURL(f.url);\n        }\n      }\n    },\n    [usingProvider],\n  );\n\n  const handleChange: ChangeEventHandler<HTMLInputElement> = (event) => {\n    if (event.currentTarget.files) {\n      add(event.currentTarget.files);\n    }\n    event.currentTarget.value = '';\n  };\n\n  const convertBlobUrlToDataUrl = async (\n    url: string,\n  ): Promise<string | null> => {\n    try {\n      const response = await fetch(url);\n      const blob = await response.blob();\n      return new Promise((resolve) => {\n        const reader = new FileReader();\n        reader.onloadend = () => resolve(reader.result as string);\n        reader.onerror = () => resolve(null);\n        reader.readAsDataURL(blob);\n      });\n    } catch {\n      return null;\n    }\n  };\n\n  const ctx = useMemo<AttachmentsContext>(\n    () => ({\n      files: files.map((item) => ({ ...item, id: item.id })),\n      add,\n      remove,\n      clear,\n      openFileDialog,\n      fileInputRef: inputRef,\n    }),\n    [files, add, remove, clear, openFileDialog],\n  );\n\n  const handleSubmit: FormEventHandler<HTMLFormElement> = (event) => {\n    event.preventDefault();\n    const form = event.currentTarget;\n    const text = usingProvider\n      ? controller.textInput.value\n      : (() => {\n          const formData = new FormData(form);\n          return (formData.get('message') as string) || '';\n        })();\n\n    if (!usingProvider) {\n      form.reset();\n    }\n\n    Promise.all(\n      files.map(async (item) => {\n        // eslint-disable-next-line @typescript-eslint/no-unused-vars\n        const { id, ...rest } = item;\n        if (rest.url && rest.url.startsWith('blob:')) {\n          const dataUrl = await convertBlobUrlToDataUrl(rest.url);\n          return { ...rest, url: dataUrl ?? rest.url } as FileUIPart;\n        }\n        return rest as FileUIPart;\n      }),\n    )\n      .then((convertedFiles: FileUIPart[]) => {\n        try {\n          const result = onSubmit({ text, files: convertedFiles }, event);\n\n          if (result instanceof Promise) {\n            result\n              .then(() => {\n                clear();\n                if (usingProvider) {\n                  controller.textInput.clear();\n                }\n              })\n              .catch(() => {\n                // Don't clear on error - user may want to retry\n              });\n          } else {\n            clear();\n            if (usingProvider) {\n              controller.textInput.clear();\n            }\n          }\n        } catch {\n          // Don't clear on error - user may want to retry\n        }\n      })\n      .catch(() => {\n        // Don't clear on error - user may want to retry\n      });\n  };\n\n  const inner = (\n    <TooltipProvider>\n      <input\n        accept={accept}\n        aria-label=\"Upload files\"\n        className=\"hidden\"\n        multiple={multiple}\n        onChange={handleChange}\n        ref={inputRef}\n        title=\"Upload files\"\n        type=\"file\"\n      />\n      <form\n        className={cn('w-full', className)}\n        onSubmit={handleSubmit}\n        ref={formRef}\n        {...props}\n      >\n        <InputGroup className=\"overflow-hidden rounded-xl bg-card dark:bg-card\">\n          {children}\n        </InputGroup>\n      </form>\n    </TooltipProvider>\n  );\n\n  return usingProvider ? (\n    inner\n  ) : (\n    <LocalAttachmentsContext.Provider value={ctx}>\n      {inner}\n    </LocalAttachmentsContext.Provider>\n  );\n};\n\n// ============================================================================\n// PromptInputBody / Header / Footer / Tools\n// ============================================================================\n\nexport type PromptInputBodyProps = HTMLAttributes<HTMLDivElement>;\n\nexport const PromptInputBody = ({\n  className,\n  ...props\n}: PromptInputBodyProps) => (\n  <div className={cn('contents', className)} {...props} />\n);\n\nexport type PromptInputHeaderProps = Omit<\n  ComponentProps<typeof InputGroupAddon>,\n  'align'\n>;\n\nexport const PromptInputHeader = ({\n  className,\n  ...props\n}: PromptInputHeaderProps) => (\n  <InputGroupAddon\n    align=\"block-start\"\n    className={cn('flex-wrap gap-1', className)}\n    {...props}\n  />\n);\n\nexport type PromptInputFooterProps = Omit<\n  ComponentProps<typeof InputGroupAddon>,\n  'align'\n>;\n\nexport const PromptInputFooter = ({\n  className,\n  ...props\n}: PromptInputFooterProps) => (\n  <InputGroupAddon\n    align=\"block-end\"\n    className={cn('justify-between gap-1', className)}\n    {...props}\n  />\n);\n\nexport type PromptInputToolsProps = HTMLAttributes<HTMLDivElement>;\n\nexport const PromptInputTools = ({\n  className,\n  ...props\n}: PromptInputToolsProps) => (\n  <div className={cn('flex items-center gap-1', className)} {...props} />\n);\n\n// ============================================================================\n// PromptInputTextarea\n// ============================================================================\n\nexport type PromptInputTextareaProps = ComponentProps<\n  typeof InputGroupTextarea\n>;\n\nexport const PromptInputTextarea = ({\n  onChange,\n  className,\n  placeholder = 'What would you like to know?',\n  ...props\n}: PromptInputTextareaProps) => {\n  const controller = useOptionalPromptInputController();\n  const attachments = usePromptInputAttachments();\n  const [isComposing, setIsComposing] = useState(false);\n\n  const handleKeyDown: KeyboardEventHandler<HTMLTextAreaElement> = (e) => {\n    if (e.key === 'Enter') {\n      if (isComposing || e.nativeEvent.isComposing) {\n        return;\n      }\n      if (e.shiftKey) {\n        return;\n      }\n      e.preventDefault();\n      const form = e.currentTarget.form;\n      const submitButton = form?.querySelector(\n        'button[type=\"submit\"]',\n      ) as HTMLButtonElement | null;\n      if (submitButton?.disabled) {\n        return;\n      }\n      form?.requestSubmit();\n    }\n\n    if (\n      e.key === 'Backspace' &&\n      e.currentTarget.value === '' &&\n      attachments.files.length > 0\n    ) {\n      e.preventDefault();\n      const lastAttachment = attachments.files.at(-1);\n      if (lastAttachment) {\n        attachments.remove(lastAttachment.id);\n      }\n    }\n  };\n\n  const handlePaste: ClipboardEventHandler<HTMLTextAreaElement> = (event) => {\n    const items = event.clipboardData?.items;\n    if (!items) return;\n    const files: File[] = [];\n    for (const item of items) {\n      if (item.kind === 'file') {\n        const file = item.getAsFile();\n        if (file) {\n          files.push(file);\n        }\n      }\n    }\n    if (files.length > 0) {\n      event.preventDefault();\n      attachments.add(files);\n    }\n  };\n\n  const controlledProps = controller\n    ? {\n        value: controller.textInput.value,\n        onChange: (e: ChangeEvent<HTMLTextAreaElement>) => {\n          controller.textInput.setInput(e.currentTarget.value);\n          onChange?.(e);\n        },\n      }\n    : {\n        onChange,\n      };\n\n  return (\n    <InputGroupTextarea\n      className={cn('field-sizing-content max-h-48 min-h-16', className)}\n      name=\"message\"\n      onCompositionEnd={() => setIsComposing(false)}\n      onCompositionStart={() => setIsComposing(true)}\n      onKeyDown={handleKeyDown}\n      onPaste={handlePaste}\n      placeholder={placeholder}\n      {...props}\n      {...controlledProps}\n    />\n  );\n};\n\n// ============================================================================\n// PromptInputButton - InputGroupButton wrapper for in-input actions\n// ============================================================================\n\nexport type PromptInputButtonProps = ComponentProps<typeof InputGroupButton> & {\n  /**\n   * Optional hover/focus tooltip. When set, the button is wrapped in a\n   * `Tooltip` (the `PromptInput` root already provides a `TooltipProvider`,\n   * so this works out of the box). Reserve it for non-critical hints such as\n   * icon labels or keyboard shortcuts.\n   */\n  tooltip?: ReactNode;\n};\n\nexport const PromptInputButton = ({\n  variant = 'ghost',\n  className,\n  size,\n  tooltip,\n  ...props\n}: PromptInputButtonProps) => {\n  const newSize =\n    size ?? (Children.count(props.children) > 1 ? 'sm' : 'icon-sm');\n\n  const button = (\n    <InputGroupButton\n      className={cn(className)}\n      size={newSize}\n      type=\"button\"\n      variant={variant}\n      {...props}\n    />\n  );\n\n  if (!tooltip) {\n    return button;\n  }\n\n  return (\n    <Tooltip>\n      <TooltipTrigger asChild>{button}</TooltipTrigger>\n      <TooltipContent>{tooltip}</TooltipContent>\n    </Tooltip>\n  );\n};\n\n// ============================================================================\n// PromptInputSubmit - status-driven submit InputGroupButton\n// ============================================================================\n\nexport type PromptInputSubmitProps = ComponentProps<typeof InputGroupButton> & {\n  status?: ChatStatus;\n  /** Optional hover/focus tooltip, wrapped via the root `TooltipProvider`. */\n  tooltip?: ReactNode;\n};\n\nexport const PromptInputSubmit = ({\n  className,\n  variant = 'default',\n  size = 'icon-sm',\n  status,\n  children,\n  tooltip,\n  ...props\n}: PromptInputSubmitProps) => {\n  let Icon: ReactNode = <CornerDownLeftIcon className=\"size-4\" />;\n\n  if (status === 'submitted') {\n    Icon = <Loader2Icon className=\"size-4 animate-spin\" />;\n  } else if (status === 'streaming') {\n    Icon = <SquareIcon className=\"size-4\" />;\n  } else if (status === 'error') {\n    Icon = <XIcon className=\"size-4\" />;\n  }\n\n  const button = (\n    <InputGroupButton\n      aria-label=\"Submit\"\n      className={cn(className)}\n      size={size}\n      type=\"submit\"\n      variant={variant}\n      {...props}\n    >\n      {children ?? Icon}\n    </InputGroupButton>\n  );\n\n  if (!tooltip) {\n    return button;\n  }\n\n  return (\n    <Tooltip>\n      <TooltipTrigger asChild>{button}</TooltipTrigger>\n      <TooltipContent>{tooltip}</TooltipContent>\n    </Tooltip>\n  );\n};\n\n// ============================================================================\n// PromptInputAttachButton - paperclip button that opens the file picker\n// ============================================================================\n\nexport type PromptInputAttachButtonProps = Omit<\n  PromptInputButtonProps,\n  'onClick'\n>;\n\nexport const PromptInputAttachButton = ({\n  children,\n  ...props\n}: PromptInputAttachButtonProps) => {\n  const attachments = usePromptInputAttachments();\n\n  return (\n    <PromptInputButton\n      aria-label=\"Attach files\"\n      onClick={() => attachments.openFileDialog()}\n      {...props}\n    >\n      {children ?? <PaperclipIcon className=\"size-4\" />}\n    </PromptInputButton>\n  );\n};\n\n// ============================================================================\n// PromptInputActionMenu - DropdownMenu wrapper for in-input actions\n// ============================================================================\n\nexport type PromptInputActionMenuProps = ComponentProps<typeof DropdownMenu>;\nexport const PromptInputActionMenu = (props: PromptInputActionMenuProps) => (\n  <DropdownMenu {...props} />\n);\n\nexport type PromptInputActionMenuTriggerProps = PromptInputButtonProps;\n\nexport const PromptInputActionMenuTrigger = ({\n  className,\n  children,\n  ...props\n}: PromptInputActionMenuTriggerProps) => (\n  <DropdownMenuTrigger asChild>\n    <PromptInputButton className={className} {...props}>\n      {children ?? <PlusIcon className=\"size-4\" />}\n    </PromptInputButton>\n  </DropdownMenuTrigger>\n);\n\nexport type PromptInputActionMenuContentProps = ComponentProps<\n  typeof DropdownMenuContent\n>;\nexport const PromptInputActionMenuContent = ({\n  className,\n  ...props\n}: PromptInputActionMenuContentProps) => (\n  <DropdownMenuContent align=\"start\" className={cn(className)} {...props} />\n);\n\nexport type PromptInputActionMenuItemProps = ComponentProps<\n  typeof DropdownMenuItem\n>;\nexport const PromptInputActionMenuItem = ({\n  className,\n  ...props\n}: PromptInputActionMenuItemProps) => (\n  <DropdownMenuItem className={cn(className)} {...props} />\n);\n\n// ============================================================================\n// PromptInputSpeechButton - Web Speech API integration\n// ============================================================================\n\n// Minimal portable types - Web Speech API isn't standardized across browsers.\ninterface PromptInputSpeechRecognition extends EventTarget {\n  continuous: boolean;\n  interimResults: boolean;\n  lang: string;\n  start(): void;\n  stop(): void;\n  onstart: ((this: PromptInputSpeechRecognition, ev: Event) => unknown) | null;\n  onend: ((this: PromptInputSpeechRecognition, ev: Event) => unknown) | null;\n  onresult:\n    | ((\n        this: PromptInputSpeechRecognition,\n        ev: PromptInputSpeechRecognitionEvent,\n      ) => unknown)\n    | null;\n  onerror:\n    | ((\n        this: PromptInputSpeechRecognition,\n        ev: PromptInputSpeechRecognitionErrorEvent,\n      ) => unknown)\n    | null;\n}\n\ninterface PromptInputSpeechRecognitionEvent extends Event {\n  results: PromptInputSpeechRecognitionResultList;\n  resultIndex: number;\n}\n\ntype PromptInputSpeechRecognitionResultList = {\n  readonly length: number;\n  item(index: number): PromptInputSpeechRecognitionResult;\n  [index: number]: PromptInputSpeechRecognitionResult;\n};\n\ntype PromptInputSpeechRecognitionResult = {\n  readonly length: number;\n  item(index: number): PromptInputSpeechRecognitionAlternative;\n  [index: number]: PromptInputSpeechRecognitionAlternative;\n  isFinal: boolean;\n};\n\ntype PromptInputSpeechRecognitionAlternative = {\n  transcript: string;\n  confidence: number;\n};\n\ninterface PromptInputSpeechRecognitionErrorEvent extends Event {\n  error: string;\n}\n\ntype SpeechRecognitionCtor = {\n  new (): PromptInputSpeechRecognition;\n};\n\ntype WindowWithSpeech = Window & {\n  SpeechRecognition?: SpeechRecognitionCtor;\n  webkitSpeechRecognition?: SpeechRecognitionCtor;\n};\n\nexport type PromptInputSpeechButtonProps = ComponentProps<\n  typeof PromptInputButton\n> & {\n  textareaRef?: RefObject<HTMLTextAreaElement | null>;\n  onTranscriptionChange?: (text: string) => void;\n  lang?: string;\n};\n\nexport const PromptInputSpeechButton = ({\n  className,\n  textareaRef,\n  onTranscriptionChange,\n  lang = 'en-US',\n  ...props\n}: PromptInputSpeechButtonProps) => {\n  const [isListening, setIsListening] = useState(false);\n  const [recognition, setRecognition] =\n    useState<PromptInputSpeechRecognition | null>(null);\n  const recognitionRef = useRef<PromptInputSpeechRecognition | null>(null);\n\n  useEffect(() => {\n    if (typeof window === 'undefined') return;\n    const w = window as WindowWithSpeech;\n    const Ctor = w.SpeechRecognition ?? w.webkitSpeechRecognition;\n    if (!Ctor) return;\n\n    const speechRecognition = new Ctor();\n\n    speechRecognition.continuous = true;\n    speechRecognition.interimResults = true;\n    speechRecognition.lang = lang;\n\n    speechRecognition.onstart = () => {\n      setIsListening(true);\n    };\n\n    speechRecognition.onend = () => {\n      setIsListening(false);\n    };\n\n    speechRecognition.onresult = (event) => {\n      let finalTranscript = '';\n\n      for (let i = event.resultIndex; i < event.results.length; i++) {\n        const result = event.results[i];\n        if (result?.isFinal) {\n          finalTranscript += result[0]?.transcript ?? '';\n        }\n      }\n\n      if (finalTranscript && textareaRef?.current) {\n        const textarea = textareaRef.current;\n        const currentValue = textarea.value;\n        const newValue =\n          currentValue + (currentValue ? ' ' : '') + finalTranscript;\n\n        textarea.value = newValue;\n        textarea.dispatchEvent(new Event('input', { bubbles: true }));\n        onTranscriptionChange?.(newValue);\n      }\n    };\n\n    speechRecognition.onerror = (event) => {\n      console.error('Speech recognition error:', event.error);\n      setIsListening(false);\n    };\n\n    recognitionRef.current = speechRecognition;\n    setRecognition(speechRecognition);\n\n    return () => {\n      if (recognitionRef.current) {\n        recognitionRef.current.stop();\n      }\n    };\n  }, [textareaRef, onTranscriptionChange, lang]);\n\n  const toggleListening = useCallback(() => {\n    if (!recognition) {\n      return;\n    }\n\n    if (isListening) {\n      recognition.stop();\n    } else {\n      recognition.start();\n    }\n  }, [recognition, isListening]);\n\n  return (\n    <PromptInputButton\n      aria-label=\"Toggle voice input\"\n      className={cn(\n        'relative transition-all duration-200',\n        isListening && 'animate-pulse bg-accent text-accent-foreground',\n        className,\n      )}\n      disabled={!recognition}\n      onClick={toggleListening}\n      {...props}\n    >\n      <MicIcon className=\"size-4\" />\n    </PromptInputButton>\n  );\n};\n\n// ============================================================================\n// PromptInputSelect - model selector built on Select from @gremorie/rx-forms\n// ============================================================================\n\nexport type PromptInputSelectProps = ComponentProps<typeof Select>;\n\nexport const PromptInputSelect = (props: PromptInputSelectProps) => (\n  <Select {...props} />\n);\n\nexport type PromptInputSelectTriggerProps = ComponentProps<\n  typeof SelectTrigger\n>;\n\nexport const PromptInputSelectTrigger = ({\n  className,\n  ...props\n}: PromptInputSelectTriggerProps) => (\n  <SelectTrigger\n    className={cn(\n      'border-none bg-transparent font-medium text-muted-foreground shadow-none transition-colors',\n      'hover:bg-accent hover:text-foreground aria-expanded:bg-accent aria-expanded:text-foreground',\n      className,\n    )}\n    {...props}\n  />\n);\n\nexport type PromptInputSelectContentProps = ComponentProps<\n  typeof SelectContent\n>;\n\nexport const PromptInputSelectContent = ({\n  className,\n  position = 'popper',\n  sideOffset = 4,\n  ...props\n}: PromptInputSelectContentProps) => (\n  <SelectContent\n    className={cn(className)}\n    position={position}\n    sideOffset={sideOffset}\n    {...props}\n  />\n);\n\nexport type PromptInputSelectItemProps = ComponentProps<typeof SelectItem>;\n\nexport const PromptInputSelectItem = ({\n  className,\n  ...props\n}: PromptInputSelectItemProps) => (\n  <SelectItem className={cn(className)} {...props} />\n);\n\nexport type PromptInputSelectValueProps = ComponentProps<typeof SelectValue>;\n\nexport const PromptInputSelectValue = ({\n  ...props\n}: PromptInputSelectValueProps) => <SelectValue {...props} />;\n\n// ============================================================================\n// PromptInputHoverCard - re-exports of HoverCard with zero-delay defaults\n// ============================================================================\n\nexport type PromptInputHoverCardProps = ComponentProps<typeof HoverCard>;\n\nexport const PromptInputHoverCard = ({\n  openDelay = 0,\n  closeDelay = 0,\n  ...props\n}: PromptInputHoverCardProps) => (\n  <HoverCard closeDelay={closeDelay} openDelay={openDelay} {...props} />\n);\n\nexport type PromptInputHoverCardTriggerProps = ComponentProps<\n  typeof HoverCardTrigger\n>;\n\nexport const PromptInputHoverCardTrigger = (\n  props: PromptInputHoverCardTriggerProps,\n) => <HoverCardTrigger {...props} />;\n\nexport type PromptInputHoverCardContentProps = ComponentProps<\n  typeof HoverCardContent\n>;\n\nexport const PromptInputHoverCardContent = ({\n  align = 'start',\n  ...props\n}: PromptInputHoverCardContentProps) => (\n  <HoverCardContent align={align} {...props} />\n);\n\n// ============================================================================\n// PromptInputCommand - command palette wrappers\n// ============================================================================\n\nexport type PromptInputCommandProps = ComponentProps<typeof Command>;\n\nexport const PromptInputCommand = ({\n  className,\n  ...props\n}: PromptInputCommandProps) => <Command className={cn(className)} {...props} />;\n\nexport type PromptInputCommandInputProps = ComponentProps<typeof CommandInput>;\n\nexport const PromptInputCommandInput = ({\n  className,\n  ...props\n}: PromptInputCommandInputProps) => (\n  <CommandInput className={cn(className)} {...props} />\n);\n\nexport type PromptInputCommandListProps = ComponentProps<typeof CommandList>;\n\nexport const PromptInputCommandList = ({\n  className,\n  ...props\n}: PromptInputCommandListProps) => (\n  <CommandList className={cn(className)} {...props} />\n);\n\nexport type PromptInputCommandEmptyProps = ComponentProps<typeof CommandEmpty>;\n\nexport const PromptInputCommandEmpty = ({\n  ...props\n}: PromptInputCommandEmptyProps) => <CommandEmpty {...props} />;\n\nexport type PromptInputCommandGroupProps = ComponentProps<typeof CommandGroup>;\n\nexport const PromptInputCommandGroup = ({\n  className,\n  ...props\n}: PromptInputCommandGroupProps) => (\n  <CommandGroup className={cn(className)} {...props} />\n);\n\nexport type PromptInputCommandItemProps = ComponentProps<typeof CommandItem>;\n\nexport const PromptInputCommandItem = ({\n  className,\n  ...props\n}: PromptInputCommandItemProps) => (\n  <CommandItem className={cn(className)} {...props} />\n);\n\nexport type PromptInputCommandSeparatorProps = ComponentProps<\n  typeof CommandSeparator\n>;\n\nexport const PromptInputCommandSeparator = ({\n  className,\n  ...props\n}: PromptInputCommandSeparatorProps) => (\n  <CommandSeparator className={cn(className)} {...props} />\n);\n\n// ============================================================================\n// PromptInputTabs* - lightweight tabbed panels inside dropdowns / menus\n// ============================================================================\n\nexport type PromptInputTabsListProps = HTMLAttributes<HTMLDivElement>;\n\nexport const PromptInputTabsList = ({\n  className,\n  ...props\n}: PromptInputTabsListProps) => <div className={cn(className)} {...props} />;\n\nexport type PromptInputTabProps = HTMLAttributes<HTMLDivElement>;\n\nexport const PromptInputTab = ({\n  className,\n  ...props\n}: PromptInputTabProps) => <div className={cn(className)} {...props} />;\n\nexport type PromptInputTabLabelProps = HTMLAttributes<HTMLHeadingElement>;\n\nexport const PromptInputTabLabel = ({\n  className,\n  ...props\n}: PromptInputTabLabelProps) => (\n  <h3\n    className={cn(\n      'mb-2 px-3 font-medium text-muted-foreground text-xs',\n      className,\n    )}\n    {...props}\n  />\n);\n\nexport type PromptInputTabBodyProps = HTMLAttributes<HTMLDivElement>;\n\nexport const PromptInputTabBody = ({\n  className,\n  ...props\n}: PromptInputTabBodyProps) => (\n  <div className={cn('space-y-1', className)} {...props} />\n);\n\nexport type PromptInputTabItemProps = HTMLAttributes<HTMLDivElement>;\n\nexport const PromptInputTabItem = ({\n  className,\n  ...props\n}: PromptInputTabItemProps) => (\n  <div\n    className={cn(\n      'flex items-center gap-2 px-3 py-2 text-xs hover:bg-accent',\n      className,\n    )}\n    {...props}\n  />\n);\n",
      "type": "registry:component",
      "target": "src/components/gremorie/ai/prompt-input/prompt-input.tsx"
    }
  ],
  "cssVars": {},
  "usage": {
    "whenToUse": "Any React-based AI chat surface - the input area where the user composes their prompt, optionally attaches files, and submits.",
    "whenNotToUse": "Plain form inputs unrelated to a conversational AI flow - use a native textarea + button instead.",
    "bestPractices": [
      "Always nest a PromptInputTextarea inside PromptInput - the parent owns the state machine.",
      "Wire PromptInputSubmit as a child element; it picks up status automatically (ready / submitted / streaming / error).",
      "Use PromptInputFooter for sticky bottom controls (tools on the left, submit on the right).",
      "Wrap the tree in PromptInputProvider only when you need to control attachments or text input from outside the form (eg. drag-to-drop across the whole page)."
    ],
    "antipatterns": [
      "Listening to onSubmit on the textarea directly - listen to the parent PromptInput onSubmit to receive the full payload.",
      "Mixing PromptInputSubmit with a custom submit button - the primitive already handles the Enter / Cmd+Enter keyboard contract.",
      "Re-implementing attachment state in the host component - drive it via the controller hook usePromptInputAttachments() or the provider."
    ],
    "api": {
      "inputs": [
        {
          "name": "onSubmit",
          "type": "(message: PromptInputMessage, e: FormEvent) => void | Promise<void>",
          "required": true,
          "description": "Fired when the user submits via Enter or by clicking PromptInputSubmit."
        },
        {
          "name": "status",
          "type": "ChatStatus ('ready' | 'submitted' | 'streaming' | 'error')",
          "required": false,
          "default": "'ready'",
          "description": "Drives the PromptInputSubmit icon (arrow / spinner / stop / X)."
        },
        {
          "name": "maxFiles",
          "type": "number",
          "required": false
        },
        {
          "name": "maxFileSize",
          "type": "number",
          "required": false,
          "description": "Bytes."
        },
        {
          "name": "accept",
          "type": "string",
          "required": false,
          "description": "MIME pattern list like 'image/*,application/pdf'."
        }
      ]
    },
    "examples": [
      {
        "title": "Basic chat input",
        "code": "<PromptInput onSubmit={(message) => sendMessage(message.text, message.files)}>\n  <PromptInputBody>\n    <PromptInputTextarea placeholder=\"Ask anything\" />\n    <PromptInputFooter>\n      <span />\n      <PromptInputSubmit status={status} />\n    </PromptInputFooter>\n  </PromptInputBody>\n</PromptInput>\n"
      },
      {
        "title": "With toolbar",
        "code": "<PromptInput onSubmit={onSubmit}>\n  <PromptInputBody>\n    <PromptInputTextarea />\n    <PromptInputFooter>\n      <PromptInputTools>\n        <PromptInputButton aria-label=\"Attach\"><Paperclip /></PromptInputButton>\n        <PromptInputButton aria-label=\"Web\"><Globe /></PromptInputButton>\n      </PromptInputTools>\n      <PromptInputSubmit status={status} />\n    </PromptInputFooter>\n  </PromptInputBody>\n</PromptInput>\n"
      }
    ]
  }
}